README.md
setup.cfg
setup.py
cerebtests/__init__.py
cerebtests/fileManager.py
cerebtests/resultsManager.py
cerebtests.egg-info/PKG-INFO
cerebtests.egg-info/SOURCES.txt
cerebtests.egg-info/dependency_links.txt
cerebtests.egg-info/requires.txt
cerebtests.egg-info/top_level.txt
cerebtests/capabilities/__init__.py
cerebtests/capabilities/cells/__init__.py
cerebtests/capabilities/cells/measurements.py
cerebtests/capabilities/cells/response.py
cerebtests/validation_tests/__init__.py
cerebtests/validation_tests/cells/__init__.py
cerebtests/validation_tests/cells/Granule/__init__.py
cerebtests/validation_tests/cells/Granule/test_for_nonadaptingGrC.py
cerebtests/validation_tests/cells/Granule/test_for_restingVm.py
cerebtests/validation_tests/cells/Granule/test_for_spontFiring.py
cerebtests/validation_tests/cells/Granule/test_sciunit_order.py
cerebtests/validation_tests/cells/Purkinje/__init__.py
cerebtests/validation_tests/cells/Purkinje/test_for_soma_Rin.py
cerebtests/validation_tests/cells/Purkinje/test_for_soma_restVm.py
cerebtests/validation_tests/cells/Purkinje/test_for_soma_spikeheight_antidromic.py