Metadata-Version: 1.1
Name: cerebtests
Version: 0.0.2
Summary: Installable package 'cerebtests' for cerebunit
Home-page: https://github.com/cerebunit/cerebtests
Author: Lungsi
Author-email: lungsi.ngwua@cnrs.fr
License: BSD Clause-3
Download-URL: https://github.com/cerebunit/cerebtests/archive/refs/tags/v0.0.2.tar.gz
Keywords: VALIDATION,CEREBELLUM,NEUROSCIENCE,MODELING,SCIENTIFIC METHOD
Platform: UNKNOWN
Classifier: Development Status :: 4 - Beta
Classifier: Intended Audience :: Developers
Classifier: License :: OSI Approved :: BSD License
Classifier: Programming Language :: Python :: 3.5
Classifier: Programming Language :: Python :: 3.6
Classifier: Programming Language :: Python :: 3.7
